geoffreyplugins/__init__.py
geoffreyplugins/pyreverse.py
geoffreyplugins/pyreverse/main.js
geoffreyplugins/pyreverse/assets/.gitkeep
geoffrey_pyreverse-0.0.1.dist-info/DESCRIPTION.rst
geoffrey_pyreverse-0.0.1.dist-info/RECORD
geoffrey_pyreverse-0.0.1.dist-info/WHEEL
geoffrey_pyreverse-0.0.1.dist-info/top_level.txt
geoffrey_pyreverse-0.0.1.dist-info/metadata.json
geoffrey_pyreverse-0.0.1.dist-info/METADATA
