Metadata-Version: 2.0
Name: geoffrey-pyreverse
Version: 0.0.1
Summary: Pyreverse : UML Diagrams for Python
Home-page: https://github.com/GeoffreyCI/geoffrey-pyreverse
Author: Roberto Abdelkader Martínez Pérez
Author-email: robertomartinezp@gmail.com
License: UNKNOWN
Platform: UNKNOWN
